stock_price_tracker/__init__.py
stock_price_tracker/tracker.py
stock_price_tracker-1.0.0.dist-info/METADATA
stock_price_tracker-1.0.0.dist-info/WHEEL
stock_price_tracker-1.0.0.dist-info/entry_points.txt
stock_price_tracker-1.0.0.dist-info/top_level.txt
stock_price_tracker-1.0.0.dist-info/RECORD
