Metadata-Version: 2.1
Name: stock_price_tracker
Version: 1.0.0
Summary: A Python package to track stock prices and send email alerts when price conditions are met.
Home-page: https://github.com/Vaishaliyadavv/stock_price_tracker.git
Author: Vaishali Yadav
Classifier: Programming Language :: Python :: 3
Classifier: License :: OSI Approved :: MIT License
Classifier: Operating System :: OS Independent
Requires-Python: >=3.6
Requires-Dist: yfinance
Requires-Dist: apscheduler
